{
  "project_info": {
    "project_number": "480321848468",
    "project_id": "whaletunes-3bf8e",
    "storage_bucket": "whaletunes-3bf8e.appspot.com"
  },
  "client": [
    {
      "client_info": {
        "mobilesdk_app_id": "1:480321848468:android:b49dbf84be23950b37a081",
        "android_client_info": {
          "package_name": "io.ProjectKraken.whaletunes"
        }
      },
      "oauth_client": [
        {
          "client_id": "480321848468-ekac05kjf9915h9o9b335hkj14jjfd50.apps.googleusercontent.com",
          "client_type": 3
        }
      ],
      "api_key": [
        {
          "current_key": "AIzaSyA9KPXqmK7RJx8tUipAQ8UjZ_H7DmIw008"
        }
      ],
      "services": {
        "appinvite_service": {
          "other_platform_oauth_client": [
            {
              "client_id": "480321848468-ekac05kjf9915h9o9b335hkj14jjfd50.apps.googleusercontent.com",
              "client_type": 3
            }
          ]
        }
      }
    }
  ],
  "configuration_version": "1"
}